phoenix5/__init__.py
phoenix5/_init_phoenix5_api.py
phoenix5/_init_phoenix6.py
phoenix5/_osx_phoenix6_pkgcfg.py
phoenix5/ctre.cpp
phoenix5/led.py
phoenix5/phoenix5_api.pc
phoenix5/py.typed
phoenix5/sensors.py
phoenix5/version.py
phoenix5/include/CTRE_LICENSE.txt
phoenix5/include/LICENSE.txt
phoenix5/include/ctre/Phoenix.h
phoenix5/include/ctre/phoenix/CANBusAddressable.h
phoenix5/include/ctre/phoenix/CANifier.h
phoenix5/include/ctre/phoenix/CANifierControlFrame.h
phoenix5/include/ctre/phoenix/CANifierFaults.h
phoenix5/include/ctre/phoenix/CANifierStatusFrame.h
phoenix5/include/ctre/phoenix/CANifierStickyFaults.h
phoenix5/include/ctre/phoenix/CANifierVelocityMeasPeriod.h
phoenix5/include/ctre/phoenix/CTRLogger.h
phoenix5/include/ctre/phoenix/Context.h
phoenix5/include/ctre/phoenix/CustomParamConfiguration.h
phoenix5/include/ctre/phoenix/ErrorCode.h
phoenix5/include/ctre/phoenix/HsvToRgb.h
phoenix5/include/ctre/phoenix/LinearInterpolation.h
phoenix5/include/ctre/phoenix/PhoenixVersion.h
phoenix5/include/ctre/phoenix/RCRadio3Ch.h
phoenix5/include/ctre/phoenix/StatusCodes.h
phoenix5/include/ctre/phoenix/Stopwatch.h
phoenix5/include/ctre/phoenix/Utilities.h
phoenix5/include/ctre/phoenix/WPI_CallbackHelper.h
phoenix5/include/ctre/phoenix/autocache.h
phoenix5/include/ctre/phoenix/export.h
phoenix5/include/ctre/phoenix/paramEnum.h
phoenix5/include/ctre/phoenix/cci/BuffTrajPointStream_CCI.h
phoenix5/include/ctre/phoenix/cci/CANdle_CCI.h
phoenix5/include/ctre/phoenix/cci/CANifier_CCI.h
phoenix5/include/ctre/phoenix/cci/CCI.h
phoenix5/include/ctre/phoenix/cci/Diagnostics_CCI.h
phoenix5/include/ctre/phoenix/cci/Logger_CCI.h
phoenix5/include/ctre/phoenix/cci/MotController_CCI.h
phoenix5/include/ctre/phoenix/cci/Orchestra_CCI.h
phoenix5/include/ctre/phoenix/cci/PDP_CCI.h
phoenix5/include/ctre/phoenix/cci/PigeonIMU_CCI.h
phoenix5/include/ctre/phoenix/cci/PlatformCAN_CCI.h
phoenix5/include/ctre/phoenix/cci/Platform_CCI.h
phoenix5/include/ctre/phoenix/cci/Unmanaged_CCI.h
robotpy_ctre-2026.1.0.dist-info/METADATA
robotpy_ctre-2026.1.0.dist-info/WHEEL
robotpy_ctre-2026.1.0.dist-info/entry_points.txt
robotpy_ctre-2026.1.0.dist-info/licenses/LICENSE
robotpy_ctre-2026.1.0.dist-info/RECORD
