Metadata-Version: 2.4
Name: robotpy-ctre
Version: 2026.1.0
Summary: Binary wrappers for the CTRE Phoenix library
Project-URL: Source code, https://github.com/robotpy/robotpy-ctre
Author-email: RobotPy Development Team <robotpy@googlegroups.com>
License-Expression: MIT
License-File: LICENSE
Requires-Dist: phoenix6~=26.1.0
Requires-Dist: wpilib<2027,>=2026.1.1
